{
  "text": "Poznejte sport podle českého sportovce",
  "questions": [
    {
      "key": "Daniel Landa",
      "values": [
        "bojový umělec",
        "automobilový závodník",
        "lední hokejista",
        "basketbalista"
      ],
      "correctIndex": 1
    },
    {
      "key": "David Krejčí",
      "values": [
        "judista",
        "lední hokejista",
        "golfista",
        "boxer"
      ],
      "correctIndex": 1
    },
    {
      "key": "Lukáš Pollert",
      "values": [
        "jezdec",
        "horolezec",
        "šachista",
        "kanoista"
      ],
      "correctIndex": 3
    },
    {
      "key": "Petr Korda",
      "values": [
        "judista",
        "fotbalista",
        "tenista",
        "šachista"
      ],
      "correctIndex": 2
    },
    {
      "key": "Radek Štěpánek",
      "values": [
        "tenista",
        "šachista",
        "judista",
        "boxer"
      ],
      "correctIndex": 0
    },
    {
      "key": "Ondřej Sekora",
      "values": [
        "ragbista",
        "lední hokejista",
        "rybář",
        "tenista"
      ],
      "correctIndex": 0
    },
    {
      "key": "Karel Brückner",
      "values": [
        "boxer",
        "fotbalista",
        "tenista",
        "automobilový závodník"
      ],
      "correctIndex": 1
    },
    {
      "key": "Pavel Bém",
      "values": [
        "horolezec",
        "golfista",
        "automobilový závodník",
        "lední hokejista"
      ],
      "correctIndex": 0
    },
    {
      "key": "Josef Rakoncaj",
      "values": [
        "golfista",
        "horolezec",
        "lední hokejista",
        "zápasník"
      ],
      "correctIndex": 1
    },
    {
      "key": "Jiří Pliska",
      "values": [
        "fotbalista",
        "horolezec",
        "basketbalista",
        "bojový umělec"
      ],
      "correctIndex": 1
    }
  ]
}