{
  "text": "Určete město podle kultury",
  "questions": [
    {
      "key": "Atomium",
      "values": [
        "Brusel",
        "Lisabon",
        "Tokio",
        "Londýn"
      ],
      "correctIndex": 0
    },
    {
      "key": "Entropa",
      "values": [
        "Tokio",
        "Brusel",
        "Stockholm",
        "Dublin"
      ],
      "correctIndex": 1
    },
    {
      "key": "The Freddie Mercury Tribute Concert",
      "values": [
        "Londýn",
        "Amsterdam",
        "Jeruzalém",
        "Lisabon"
      ],
      "correctIndex": 0
    },
    {
      "key": "Centre Georges Pompidou",
      "values": [
        "Ósaka",
        "Stockholm",
        "Reykjavík",
        "Paříž"
      ],
      "correctIndex": 3
    },
    {
      "key": "Dům Anne Frankové",
      "values": [
        "Dublin",
        "Brusel",
        "Amsterdam",
        "Kodaň"
      ],
      "correctIndex": 2
    },
    {
      "key": "Royal Albert Hall",
      "values": [
        "Londýn",
        "Stockholm",
        "Paříž",
        "Kodaň"
      ],
      "correctIndex": 0
    },
    {
      "key": "Národní parlamentní knihovna Japonska",
      "values": [
        "Brusel",
        "Ósaka",
        "Paříž",
        "Tokio"
      ],
      "correctIndex": 3
    },
    {
      "key": "Královská společnost",
      "values": [
        "Tokio",
        "Londýn",
        "Kodaň",
        "Tel Aviv"
      ],
      "correctIndex": 1
    },
    {
      "key": "Eurovision Song Contest 2019",
      "values": [
        "Reykjavík",
        "Stockholm",
        "Tokio",
        "Tel Aviv"
      ],
      "correctIndex": 3
    },
    {
      "key": "Expo 2025",
      "values": [
        "Brusel",
        "Amsterdam",
        "Dublin",
        "Ósaka"
      ],
      "correctIndex": 3
    }
  ]
}