{
  "text": "Jedná se o [země] římského katolíka?",
  "questions": [
    {
      "key": "Jan Kraus",
      "values": [
        "britského",
        "francouzského",
        "českého",
        "amerického"
      ],
      "correctIndex": 2
    },
    {
      "key": "Galileo Galilei",
      "values": [
        "amerického",
        "italského",
        "portugalského",
        "německého"
      ],
      "correctIndex": 1
    },
    {
      "key": "Caravaggio",
      "values": [
        "italského",
        "maďarského",
        "švýcarského",
        "českého"
      ],
      "correctIndex": 0
    },
    {
      "key": "Jan Sokol",
      "values": [
        "českého",
        "maďarského",
        "německého",
        "francouzského"
      ],
      "correctIndex": 0
    },
    {
      "key": "Petr Eben",
      "values": [
        "portugalského",
        "italského",
        "českého",
        "francouzského"
      ],
      "correctIndex": 2
    },
    {
      "key": "Jiří Lobkowicz",
      "values": [
        "italského",
        "německého",
        "francouzského",
        "českého"
      ],
      "correctIndex": 3
    },
    {
      "key": "Albano Carrisi",
      "values": [
        "italského",
        "portugalského",
        "britského",
        "kanadského"
      ],
      "correctIndex": 0
    },
    {
      "key": "Giovanni Pierluigi da Palestrina",
      "values": [
        "švýcarského",
        "italského",
        "kanadského",
        "amerického"
      ],
      "correctIndex": 1
    },
    {
      "key": "Torquato Tasso",
      "values": [
        "francouzského",
        "německého",
        "italského",
        "kanadského"
      ],
      "correctIndex": 2
    },
    {
      "key": "Matylda Bavorská",
      "values": [
        "maďarského",
        "švýcarského",
        "britského",
        "německého"
      ],
      "correctIndex": 3
    }
  ]
}