{
  "text": "Jde o [země] fotbalového reprezentanta?",
  "questions": [
    {
      "key": "Roberto Baggio",
      "values": [
        "nigerijského",
        "chorvatského",
        "kamerunského",
        "italského"
      ],
      "correctIndex": 3
    },
    {
      "key": "Steven Gerrard",
      "values": [
        "německého",
        "senegalského",
        "anglického",
        "maďarského"
      ],
      "correctIndex": 2
    },
    {
      "key": "Libor Sionko",
      "values": [
        "ruského",
        "českého",
        "nigerijského",
        "senegalského"
      ],
      "correctIndex": 1
    },
    {
      "key": "Aleksandar Mitrović",
      "values": [
        "srbského",
        "ghanského",
        "kostarického",
        "belgického"
      ],
      "correctIndex": 0
    },
    {
      "key": "Hugo Sánchez",
      "values": [
        "mexického",
        "švédského",
        "ekvádorského",
        "argentinského"
      ],
      "correctIndex": 0
    },
    {
      "key": "Michael Essien",
      "values": [
        "rumunského",
        "ghanského",
        "československého",
        "rakouského"
      ],
      "correctIndex": 1
    },
    {
      "key": "Radek Šírl",
      "values": [
        "velšského",
        "českého",
        "sovětského",
        "arménského"
      ],
      "correctIndex": 1
    },
    {
      "key": "Brian Laudrup",
      "values": [
        "dánského",
        "německého",
        "finského",
        "kostarického"
      ],
      "correctIndex": 0
    },
    {
      "key": "Giorgi Čakvetadze",
      "values": [
        "maďarského",
        "gruzínského",
        "australského",
        "chilského"
      ],
      "correctIndex": 1
    },
    {
      "key": "Hatem Ben Arfa",
      "values": [
        "bulharského",
        "nizozemského",
        "francouzského",
        "španělského"
      ],
      "correctIndex": 2
    }
  ]
}