{
  "text": "Určete zemi podle ostrova",
  "questions": [
    {
      "key": "Niue",
      "values": [
        "Nový Zéland",
        "Japonsko",
        "Kapverdy",
        "Severní Mariany"
      ],
      "correctIndex": 0
    },
    {
      "key": "Gozo",
      "values": [
        "Malta",
        "Vietnam",
        "Dominikánská republika",
        "Norsko"
      ],
      "correctIndex": 0
    },
    {
      "key": "Sveti Stefan",
      "values": [
        "Ukrajina",
        "Černá Hora",
        "Dominikánská republika",
        "Rovníková Guinea"
      ],
      "correctIndex": 1
    },
    {
      "key": "Nosy Be",
      "values": [
        "Dominikánská republika",
        "Rakousko",
        "Kubo",
        "Madagaskar"
      ],
      "correctIndex": 3
    },
    {
      "key": "Saipan",
      "values": [
        "Kubo",
        "Mauricius",
        "Ukrajina",
        "Severní Mariany"
      ],
      "correctIndex": 3
    },
    {
      "key": "Ostrov Markéta",
      "values": [
        "Austrálie",
        "Česko",
        "Rovníková Guinea",
        "Severní Mariany"
      ],
      "correctIndex": 1
    },
    {
      "key": "Chortycja",
      "values": [
        "Ukrajina",
        "Vietnam",
        "Nizozemsko",
        "Česko"
      ],
      "correctIndex": 0
    },
    {
      "key": "Ostrov Mládeže",
      "values": [
        "Kubo",
        "Vietnam",
        "Srí Lanka",
        "Papua Nová Guinea"
      ],
      "correctIndex": 0
    },
    {
      "key": "Myší zámek",
      "values": [
        "Cookovy ostrovy",
        "Česko",
        "Malta",
        "Rovníková Guinea"
      ],
      "correctIndex": 1
    },
    {
      "key": "Šikotan",
      "values": [
        "Česko",
        "Venezuela",
        "Malta",
        "Japonsko"
      ],
      "correctIndex": 3
    }
  ]
}