{
  "text": "Poznejte zemi podle politické strany",
  "questions": [
    {
      "key": "Občanské fórum",
      "values": [
        "Angola",
        "Spojené království",
        "Pero",
        "Československo"
      ],
      "correctIndex": 3
    },
    {
      "key": "Národní obec fašistická",
      "values": [
        "Polsko",
        "Švédsko",
        "Finsko",
        "Československo"
      ],
      "correctIndex": 3
    },
    {
      "key": "Muslimské bratrstvo",
      "values": [
        "Slovensko",
        "Egypt",
        "Rusko",
        "Libanon"
      ],
      "correctIndex": 1
    },
    {
      "key": "Svobodná demokratická strana",
      "values": [
        "Egypt",
        "Německo",
        "Rusko",
        "Itálie"
      ],
      "correctIndex": 1
    },
    {
      "key": "SEN 21",
      "values": [
        "Spojené království",
        "Izrael",
        "Česko",
        "Španělsko"
      ],
      "correctIndex": 2
    },
    {
      "key": "Moravské zemské hnutí",
      "values": [
        "Egypt",
        "Španělsko",
        "Finsko",
        "Česko"
      ],
      "correctIndex": 3
    },
    {
      "key": "Strana regionů",
      "values": [
        "Ukrajina",
        "Švédsko",
        "Rusko",
        "Československo"
      ],
      "correctIndex": 0
    },
    {
      "key": "Koalice radikální levice",
      "values": [
        "Spojené království",
        "Řecko",
        "Švédsko",
        "Egypt"
      ],
      "correctIndex": 1
    },
    {
      "key": "Podemos",
      "values": [
        "Irsko",
        "Itálie",
        "Španělsko",
        "Libanon"
      ],
      "correctIndex": 2
    },
    {
      "key": "Romská občanská iniciativa",
      "values": [
        "Slovinsko",
        "Československo",
        "Finsko",
        "Rakousko"
      ],
      "correctIndex": 1
    }
  ]
}