{
  "text": "Jedná se o [země] zpěvačku?",
  "questions": [
    {
      "key": "Dara Rolins",
      "values": [
        "slovenskou",
        "německou",
        "srbskou",
        "kubánskou"
      ],
      "correctIndex": 0
    },
    {
      "key": "Victoria Beckham",
      "values": [
        "německou",
        "britskou",
        "norskou",
        "kanadskou"
      ],
      "correctIndex": 1
    },
    {
      "key": "Enya",
      "values": [
        "uruguayskou",
        "islandskou",
        "irskou",
        "srbskou"
      ],
      "correctIndex": 2
    },
    {
      "key": "Cass Elliot",
      "values": [
        "americkou",
        "portugalskou",
        "španělskou",
        "chorvatskou"
      ],
      "correctIndex": 0
    },
    {
      "key": "Pavlína Jíšová",
      "values": [
        "nizozemskou",
        "norskou",
        "indickou",
        "českou"
      ],
      "correctIndex": 3
    },
    {
      "key": "Marcela Laiferová",
      "values": [
        "nizozemskou",
        "řeckou",
        "irskou",
        "slovenskou"
      ],
      "correctIndex": 3
    },
    {
      "key": "Michaela Pašteková",
      "values": [
        "indickou",
        "britskou",
        "slovenskou",
        "peruánskou"
      ],
      "correctIndex": 2
    },
    {
      "key": "Joss Stone",
      "values": [
        "italskou",
        "českou",
        "kubánskou",
        "britskou"
      ],
      "correctIndex": 3
    },
    {
      "key": "Nora Arnezederová",
      "values": [
        "portugalskou",
        "indickou",
        "kolumbijskou",
        "francouzskou"
      ],
      "correctIndex": 3
    },
    {
      "key": "Taryn Manning",
      "values": [
        "americkou",
        "mexickou",
        "finskou",
        "brazilskou"
      ],
      "correctIndex": 0
    }
  ]
}