{
  "text": "Jedná se o [země] videohru?",
  "questions": [
    {
      "key": "Brawl Stars",
      "values": [
        "australskou",
        "britskou",
        "finskou",
        "dánskou"
      ],
      "correctIndex": 2
    },
    {
      "key": "Escape from Tarkov",
      "values": [
        "srbskou",
        "polskou",
        "ruskou",
        "slovenskou"
      ],
      "correctIndex": 2
    },
    {
      "key": "Genshin Impact",
      "values": [
        "čínskou",
        "ukrajinskou",
        "rakouskou",
        "ruskou"
      ],
      "correctIndex": 0
    },
    {
      "key": "Far Cry 4",
      "values": [
        "kanadskou",
        "britskou",
        "slovenskou",
        "německou"
      ],
      "correctIndex": 0
    },
    {
      "key": "Thief",
      "values": [
        "čínskou",
        "jihokorejskou",
        "kanadskou",
        "německou"
      ],
      "correctIndex": 2
    },
    {
      "key": "TrackMania",
      "values": [
        "kanadskou",
        "francouzskou",
        "americkou",
        "nizozemskou"
      ],
      "correctIndex": 1
    },
    {
      "key": "Kantai Collection",
      "values": [
        "švédskou",
        "japonskou",
        "finskou",
        "běloruskou"
      ],
      "correctIndex": 1
    },
    {
      "key": "The Elder Scrolls Online",
      "values": [
        "ukrajinskou",
        "polskou",
        "rakouskou",
        "americkou"
      ],
      "correctIndex": 3
    },
    {
      "key": "Lineage II",
      "values": [
        "jihokorejskou",
        "běloruskou",
        "německou",
        "britskou"
      ],
      "correctIndex": 0
    },
    {
      "key": "Stronghold Crusader",
      "values": [
        "finskou",
        "britskou",
        "polskou",
        "americkou"
      ],
      "correctIndex": 1
    }
  ]
}