{
  "text": "Poznejte rok podle bitvy",
  "questions": [
    {
      "key": "Bitva na Sommě",
      "values": [
        "1415",
        "805",
        "1945",
        "1916"
      ],
      "correctIndex": 3
    },
    {
      "key": "Bitva u Lepanta",
      "values": [
        "1456",
        "1605",
        "1571",
        "1702"
      ],
      "correctIndex": 2
    },
    {
      "key": "Sacco di Roma",
      "values": [
        "1485",
        "1745",
        "1527",
        "1177"
      ],
      "correctIndex": 2
    },
    {
      "key": "Bitva u Bosworthu",
      "values": [
        "1187",
        "1485",
        "1919",
        "1647"
      ],
      "correctIndex": 1
    },
    {
      "key": "Druhá bitva u Yper",
      "values": [
        "849",
        "1451",
        "1915",
        "1953"
      ],
      "correctIndex": 2
    },
    {
      "key": "Operace Dragoon",
      "values": [
        "1571",
        "1471",
        "1944",
        "1621"
      ],
      "correctIndex": 2
    },
    {
      "key": "Druhá bitva o Charkov",
      "values": [
        "1942",
        "1793",
        "1865",
        "1917"
      ],
      "correctIndex": 0
    },
    {
      "key": "Bitva u Malojaroslavce",
      "values": [
        "1631",
        "1812",
        "1526",
        "1643"
      ],
      "correctIndex": 1
    },
    {
      "key": "Bitva u Partizánské Ľupči",
      "values": [
        "1307",
        "1815",
        "1947",
        "1621"
      ],
      "correctIndex": 2
    },
    {
      "key": "Bitva u Rosebudu",
      "values": [
        "1876",
        "1444",
        "1757",
        "1859"
      ],
      "correctIndex": 0
    }
  ]
}