{
  "text": "Jde o [země] evropského podnikatele?",
  "questions": [
    {
      "key": "Alexej Navalnyj",
      "values": [
        "švédského",
        "rakouského",
        "monackého",
        "ruského"
      ],
      "correctIndex": 3
    },
    {
      "key": "Tomáš Březina",
      "values": [
        "českého",
        "švýcarského",
        "ukrajinského",
        "italského"
      ],
      "correctIndex": 0
    },
    {
      "key": "Vlastislav Bříza",
      "values": [
        "českého",
        "rakouského",
        "ukrajinského",
        "polského"
      ],
      "correctIndex": 0
    },
    {
      "key": "Filip Hausknecht",
      "values": [
        "švédského",
        "českého",
        "belgického",
        "slovinského"
      ],
      "correctIndex": 1
    },
    {
      "key": "Hugo Ferdinand Boss",
      "values": [
        "německého",
        "britského",
        "švédského",
        "polského"
      ],
      "correctIndex": 0
    },
    {
      "key": "Marcel Gecov",
      "values": [
        "řeckého",
        "nizozemského",
        "dánského",
        "českého"
      ],
      "correctIndex": 3
    },
    {
      "key": "Jarda Hypochondr",
      "values": [
        "českého",
        "rakouského",
        "litevského",
        "řeckého"
      ],
      "correctIndex": 0
    },
    {
      "key": "Paul de Senneville",
      "values": [
        "dánského",
        "francouzského",
        "švédského",
        "českého"
      ],
      "correctIndex": 1
    },
    {
      "key": "John Jacob Astor",
      "values": [
        "německého",
        "italského",
        "dánského",
        "slovenského"
      ],
      "correctIndex": 0
    },
    {
      "key": "Josef Starkl",
      "values": [
        "belgického",
        "ruského",
        "rakouského",
        "nizozemského"
      ],
      "correctIndex": 2
    }
  ]
}