{
  "text": "Poznejte interpreta podle písně",
  "questions": [
    {
      "key": "Nothing Else Matters",
      "values": [
        "Jaroslav Hutka",
        "Metallica",
        "Rammstein",
        "Michael Jackson"
      ],
      "correctIndex": 1
    },
    {
      "key": "Nafrněná",
      "values": [
        "Elton John",
        "Barbora Poláková",
        "Lynyrd Skynyrd",
        "The Beatles"
      ],
      "correctIndex": 1
    },
    {
      "key": "Hey Jude",
      "values": [
        "The Beatles",
        "Led Zeppelin",
        "Depeche Mode",
        "The Beach Boys"
      ],
      "correctIndex": 0
    },
    {
      "key": "Ghosts Again",
      "values": [
        "Lou Reed",
        "Depeche Mode",
        "Michael Jackson",
        "Rammstein"
      ],
      "correctIndex": 1
    },
    {
      "key": "Layla",
      "values": [
        "Jimi Hendrix",
        "Barbora Poláková",
        "Eric Clapton",
        "Depeche Mode"
      ],
      "correctIndex": 2
    },
    {
      "key": "Moonlight Shadow",
      "values": [
        "Mike Oldfield",
        "Katy Perry",
        "Falco",
        "Depeche Mode"
      ],
      "correctIndex": 0
    },
    {
      "key": "Candle in the Wind",
      "values": [
        "Status Quo",
        "Elton John",
        "Jiří Suchý",
        "Eric Clapton"
      ],
      "correctIndex": 1
    },
    {
      "key": "Space Oddity",
      "values": [
        "Rammstein",
        "David Bowie",
        "Depeche Mode",
        "Status Quo"
      ],
      "correctIndex": 1
    },
    {
      "key": "Shadow on the Wall",
      "values": [
        "Mike Oldfield",
        "Karel Gott",
        "Jimi Hendrix",
        "Pink Floyd"
      ],
      "correctIndex": 0
    },
    {
      "key": "Pussy",
      "values": [
        "Jaroslav Hutka",
        "Rammstein",
        "Karel Gott",
        "Karol Duchoň"
      ],
      "correctIndex": 1
    }
  ]
}