{
  "id": "20",
  "text": "Ve kterém roce došlo k této události?",
  "questions":
  [
    {
      "name": "Založení NATO",
      "value": "1949"
    },
    {
      "name": "Války o rakouské dědictví",
      "value": "1740"
    },
    {
      "name": "Toleranční patent",
      "value": "1781"
    },
    {
      "name": "První telefon a první telefonní hovor",
      "value": "1876"
    },
    {
      "name": "První slavnostní otevření Národního divadla",
      "value": "1881"
    },
    {
      "name": "Centrum Kutné Hory bylo zapsáno na seznam světového dědictví UNESCO",
      "value": "1995"
    },
    {
      "name": "Založeno Pruské království",
      "value": "1701"
    },
    {
      "name": "V Sovětském svazu proběhl tzv. Srpnový puč",
      "value": "1991"
    },
    {
      "name": "Velká Británie opouští EU",
      "value": "2020"
    },
    {
      "name": "V Londýně vypukla morová pandemie",
      "value": "1665"
    }
  ]
}
