{
  "text": "Jedná se o [země] aktivistu?",
  "questions": [
    {
      "key": "Jindřich Rajchl",
      "values": [
        "australského",
        "českého",
        "jihoafrického",
        "indického"
      ],
      "correctIndex": 1
    },
    {
      "key": "Jana Zwyrtek Hamplová",
      "values": [
        "amerického",
        "českého",
        "kanadského",
        "australského"
      ],
      "correctIndex": 1
    },
    {
      "key": "Claudia Cardinalová",
      "values": [
        "amerického",
        "indického",
        "italského",
        "českého"
      ],
      "correctIndex": 2
    },
    {
      "key": "Nelson Mandela",
      "values": [
        "jihoafrického",
        "francouzského",
        "amerického",
        "ruského"
      ],
      "correctIndex": 0
    },
    {
      "key": "Jan Ruml",
      "values": [
        "německého",
        "indického",
        "ruského",
        "českého"
      ],
      "correctIndex": 3
    },
    {
      "key": "Břetislav Rychlík",
      "values": [
        "běloruského",
        "amerického",
        "českého",
        "kanadského"
      ],
      "correctIndex": 2
    },
    {
      "key": "Timofej Kožuchov",
      "values": [
        "jihoafrického",
        "českého",
        "slovenského",
        "italského"
      ],
      "correctIndex": 1
    },
    {
      "key": "Svjatlana Cichanouská",
      "values": [
        "německého",
        "běloruského",
        "kanadského",
        "francouzského"
      ],
      "correctIndex": 1
    },
    {
      "key": "Joe Rogan",
      "values": [
        "amerického",
        "jihoafrického",
        "českého",
        "ruského"
      ],
      "correctIndex": 0
    },
    {
      "key": "Michael Stipe",
      "values": [
        "francouzského",
        "běloruského",
        "amerického",
        "australského"
      ],
      "correctIndex": 2
    }
  ]
}