{
  "text": "Jde o [země] astronoma?",
  "questions": [
    {
      "key": "Galileo Galilei",
      "values": [
        "ruského",
        "italského",
        "polského",
        "dánského"
      ],
      "correctIndex": 1
    },
    {
      "key": "Milan Rastislav Štefánik",
      "values": [
        "amerického",
        "polského",
        "italského",
        "slovenského"
      ],
      "correctIndex": 3
    },
    {
      "key": "Mikuláš Koperník",
      "values": [
        "švédského",
        "švýcarského",
        "polského",
        "ruského"
      ],
      "correctIndex": 2
    },
    {
      "key": "Johannes Kepler",
      "values": [
        "amerického",
        "švýcarského",
        "polského",
        "německého"
      ],
      "correctIndex": 3
    },
    {
      "key": "Tycho Brahe",
      "values": [
        "italského",
        "amerického",
        "polského",
        "dánského"
      ],
      "correctIndex": 3
    },
    {
      "key": "Jiří Grygar",
      "values": [
        "dánského",
        "ruského",
        "německého",
        "českého"
      ],
      "correctIndex": 3
    },
    {
      "key": "Giordano Bruno",
      "values": [
        "německého",
        "slovenského",
        "českého",
        "italského"
      ],
      "correctIndex": 3
    },
    {
      "key": "Carl Friedrich Gauss",
      "values": [
        "amerického",
        "německého",
        "švýcarského",
        "slovenského"
      ],
      "correctIndex": 1
    },
    {
      "key": "Alexander von Humboldt",
      "values": [
        "dánského",
        "německého",
        "českého",
        "slovenského"
      ],
      "correctIndex": 1
    },
    {
      "key": "Michail Lomonosov",
      "values": [
        "italského",
        "ruského",
        "dánského",
        "amerického"
      ],
      "correctIndex": 1
    }
  ]
}